nbs_viewer/__init__.py
nbs_viewer/logging_setup.py
nbs_viewer/mainWidget.py
nbs_viewer/search.py
nbs_viewer/utils.py
nbs_viewer/viewer.py
nbs_viewer/models/__init__.py
nbs_viewer/models/app_model.py
nbs_viewer/models/catalog/base.py
nbs_viewer/models/catalog/bluesky.py
nbs_viewer/models/catalog/chunkCache.py
nbs_viewer/models/catalog/kafka.py
nbs_viewer/models/catalog/source_models.py
nbs_viewer/models/catalog/table.py
nbs_viewer/models/catalog/worker_pool.py
nbs_viewer/models/data/__init__.py
nbs_viewer/models/data/base.py
nbs_viewer/models/data/bluesky.py
nbs_viewer/models/data/combined.py
nbs_viewer/models/data/kafka.py
nbs_viewer/models/data/nbs.py
nbs_viewer/models/plot/combinedRunModel.py
nbs_viewer/models/plot/displayManager.py
nbs_viewer/models/plot/displayRegistry.py
nbs_viewer/models/plot/plotDataModel.py
nbs_viewer/models/plot/runListModel.py
nbs_viewer/models/plot/runModel.py
nbs_viewer/views/__init__.py
nbs_viewer/views/catalog/__init__.py
nbs_viewer/views/catalog/base.py
nbs_viewer/views/catalog/catalogTree.py
nbs_viewer/views/catalog/kafka.py
nbs_viewer/views/common/__init__.py
nbs_viewer/views/common/panel.py
nbs_viewer/views/dataSource/dataSource.py
nbs_viewer/views/dataSource/dataSourceSwitcher.py
nbs_viewer/views/dataSource/runListView.py
nbs_viewer/views/dataSource/tiledAuth.py
nbs_viewer/views/display/displayControl.py
nbs_viewer/views/display/mainDisplay.py
nbs_viewer/views/display/plotDisplay.py
nbs_viewer/views/plot/__init__.py
nbs_viewer/views/plot/imageGridWidget.py
nbs_viewer/views/plot/metadataView.py
nbs_viewer/views/plot/plotControl.py
nbs_viewer/views/plot/plotDimensionWidget.py
nbs_viewer/views/plot/plotWidget.py
nbs_viewer/views/plot/controls/auto_add.py
nbs_viewer/views/plot/controls/base.py
nbs_viewer/views/plot/controls/dynamic_update.py
nbs_viewer/views/plot/controls/retain_selection.py
nbs_viewer/views/plot/controls/run_display.py
nbs_viewer/views/plot/controls/transform.py
nbs_viewer/widgets/kafkaViewerTab.py
nbs_viewer-0.3.4.dist-info/licenses/LICENSE
nbs_viewer-0.3.4.dist-info/METADATA
nbs_viewer-0.3.4.dist-info/WHEEL
nbs_viewer-0.3.4.dist-info/entry_points.txt
nbs_viewer-0.3.4.dist-info/top_level.txt
nbs_viewer-0.3.4.dist-info/RECORD
