Metadata-Version: 2.4
Name: nbs-viewer
Version: 0.3.4
Summary: A simple viewer application for data stored in a Blueksy-Tiled database.
Author-email: Charles Titus <ctitus@bnl.gov>
Project-URL: Homepage, https://github.com/xraygui/nbs-viewer
Project-URL: Issues, https://github.com/xraygui/nbs-viewer/issues
Keywords: tiled,viewer
Classifier: Programming Language :: Python :: 3
Classifier: License :: Public Domain
Classifier: Operating System :: OS Independent
Classifier: Intended Audience :: Science/Research
License-File: LICENSE
Requires-Dist: numpy
Requires-Dist: qtpy
Requires-Dist: matplotlib
Requires-Dist: tiled>=0.1.0b17
Requires-Dist: bluesky-widgets>=0.0.15
Requires-Dist: pyzmq
Requires-Dist: bluesky-kafka
Requires-Dist: nslsii
Requires-Dist: databroker[back-compat,client,server]>=2.0.0b57
Requires-Dist: bluesky-tiled-plugins>=2.0.0b59
Requires-Dist: asteval
Requires-Dist: tomli>=2.0.0; python_version < "3.11"
Dynamic: license-file
